hgenfw/__init__.py
hgenfw/hfilegen.py
hgenfw/myhd4pyd.py
hgenfw-0.0.1.dist-info/LICENSE
hgenfw-0.0.1.dist-info/METADATA
hgenfw-0.0.1.dist-info/WHEEL
hgenfw-0.0.1.dist-info/top_level.txt
hgenfw-0.0.1.dist-info/RECORD
